totvsecm/BaseService.py
totvsecm/CardService.py
totvsecm/DocumentService.py
totvsecm/WorkflowEngineService.py
totvsecm/__init__.py
totvsecm-1.1.0.dist-info/LICENSE
totvsecm-1.1.0.dist-info/METADATA
totvsecm-1.1.0.dist-info/WHEEL
totvsecm-1.1.0.dist-info/top_level.txt
totvsecm-1.1.0.dist-info/RECORD
